heimdall/__init__.py
heimdall/base.py
heimdall_debugger-0.0.1.dist-info/METADATA
heimdall_debugger-0.0.1.dist-info/WHEEL
heimdall_debugger-0.0.1.dist-info/top_level.txt
heimdall_debugger-0.0.1.dist-info/RECORD
