Metadata-Version: 2.1
Name: heimdall-debugger
Version: 0.0.1
Summary: A small example package
Home-page: https://github.com/MechaCoder/heimdall
Author: Matthew Proudman
Author-email: proudmandandc@gmail.com
License: UNKNOWN
Platform: UNKNOWN
Classifier: Programming Language :: Python :: 3
Classifier: License :: OSI Approved :: MIT License
Classifier: Operating System :: OS Independent
Requires-Python: >=3.7
Requires-Dist: rich
